Chokkhu/__init__.py
Chokkhu/custom_exception.py
Chokkhu/logger.py
Chokkhu/DeepLearningModel/__init__.py
Chokkhu/DeepLearningModel/Summary/__init__.py
Chokkhu/DeepLearningModel/Summary/plots.py
Chokkhu/DeepLearningModel/eda/__init__.py
Chokkhu/DeepLearningModel/eda/image_eda.py
Chokkhu/DeepLearningModel/preprocessing/__init__.py
Chokkhu/DeepLearningModel/preprocessing/image_preprocess.py
chokkhu-0.1.3.dist-info/licenses/LICENSE
chokkhu-0.1.3.dist-info/METADATA
chokkhu-0.1.3.dist-info/WHEEL
chokkhu-0.1.3.dist-info/top_level.txt
chokkhu-0.1.3.dist-info/RECORD
